{
  "source": "behindthewalls.com",
  "jobOpportunitiesUrl": "https://www.behindthewalls.com/job-opportunities",
  "updatedAt": "2026-04-28T08:41:02.197Z",
  "positions": [
    {
      "id": "regional-director",
      "title": "Regional Director",
      "description": "The purpose of the regional director is to provide leadership in their respective territory. The regional director will establish new relationships while maintaining and strengthening existing ones as it relates to the mission of the organization by raising up teams and volunteers by equipping and igniting teammates in preparation for sharing their faith in the areas of Day of Champions events and beyond. Be a valuable team member and follow the lead of respective home office team members in the areas of development, IT, Communications, and Finance.",
      "jobDescriptionUrl": "https://irp.cdn-website.com/cb495078/files/uploaded/Regional_Director+%281%29.pdf",
      "lastScrapedAt": "2026-04-28T08:41:02.194Z"
    }
  ]
}